<annotation>
	<folder>docs</folder>
	<filename>inv-0167.jpg</filename>
	<path>/home/bruenor/pr/tab_net/CUSTOM/1C_dataset/docs/inv-0167.jpg</path>
	<source>
		<database>Unknown</database>
	</source>
	<size>
		<width>1653</width>
		<height>2339</height>
		<depth>3</depth>
	</size>
	<segmented>0</segmented>
	<object>
		<name>bordered</name>
		<pose>Unspecified</pose>
		<truncated>0</truncated>
		<difficult>0</difficult>
		<bndbox>
			<xmin>100</xmin>
			<ymin>74</ymin>
			<xmax>1391</xmax>
			<ymax>333</ymax>
		</bndbox>
	</object>
	<object>
		<name>bordered</name>
		<pose>Unspecified</pose>
		<truncated>0</truncated>
		<difficult>0</difficult>
		<bndbox>
			<xmin>91</xmin>
			<ymin>630</ymin>
			<xmax>1374</xmax>
			<ymax>791</ymax>
		</bndbox>
	</object>
</annotation>
