<annotation>
	<folder>docs</folder>
	<filename>inv-0275.jpg</filename>
	<path>/home/bruenor/pr/tab_net/CUSTOM/1C_dataset/docs/inv-0275.jpg</path>
	<source>
		<database>Unknown</database>
	</source>
	<size>
		<width>1653</width>
		<height>2339</height>
		<depth>3</depth>
	</size>
	<segmented>0</segmented>
	<object>
		<name>bordered</name>
		<pose>Unspecified</pose>
		<truncated>0</truncated>
		<difficult>0</difficult>
		<bndbox>
			<xmin>124</xmin>
			<ymin>343</ymin>
			<xmax>1607</xmax>
			<ymax>667</ymax>
		</bndbox>
	</object>
	<object>
		<name>bordered</name>
		<pose>Unspecified</pose>
		<truncated>0</truncated>
		<difficult>0</difficult>
		<bndbox>
			<xmin>121</xmin>
			<ymin>1009</ymin>
			<xmax>1609</xmax>
			<ymax>1138</ymax>
		</bndbox>
	</object>
</annotation>
